icon_set/__init__.py
icon_set/cli.py
icon_set/exceptions.py
icon_set/header.py
icon_set/icon_data.py
icon_set/icon_set.py
icon_set/icon_type.py
icon_set-0.1.0.dist-info/DESCRIPTION.rst
icon_set-0.1.0.dist-info/METADATA
icon_set-0.1.0.dist-info/RECORD
icon_set-0.1.0.dist-info/WHEEL
icon_set-0.1.0.dist-info/entry_points.txt
icon_set-0.1.0.dist-info/metadata.json
icon_set-0.1.0.dist-info/top_level.txt
