Metadata-Version: 2.0
Name: icon-set
Version: 0.1.0
Summary: Utility tool to help you create Apple Icon Set files.
Home-page: https://github.com/s16h/icon_set
Author: Shahriar Tajbakhsh
Author-email: sh.tajbakhsh@gmail.com
License: MIT license
Keywords: icon_set
Platform: UNKNOWN
Classifier: Development Status :: 2 - Pre-Alpha
Classifier: Intended Audience :: Developers
Classifier: License :: OSI Approved :: MIT License
Classifier: Natural Language :: English
Classifier: Programming Language :: Python :: 2
Classifier: Programming Language :: Python :: 2.7
Classifier: Programming Language :: Python :: 3
Classifier: Programming Language :: Python :: 3.3
Classifier: Programming Language :: Python :: 3.4
Classifier: Programming Language :: Python :: 3.5
Requires-Dist: Click (>=6.0)
Requires-Dist: Pillow (==4.0.0)
